mailshell/__init__.py
mailshell/app.py
mailshell/email_checker.py
mailshell/email_logo.py
mailshell/helper.py
mailshell/mail_checker.py
mailshell/mail_shell.py
mailshell-1.4.10.dist-info/LICENSE
mailshell-1.4.10.dist-info/METADATA
mailshell-1.4.10.dist-info/WHEEL
mailshell-1.4.10.dist-info/entry_points.txt
mailshell-1.4.10.dist-info/top_level.txt
mailshell-1.4.10.dist-info/RECORD
