Metadata-Version: 2.1
Name: mailshell
Version: 1.4.10
Summary: Send and check emails faster from the terminal
Home-page: https://github.com/malkiAbdoo/mailshell
Author: Malki Abderrahman
Author-email: abdo.malkiep@gmail.com
License: UNKNOWN
Project-URL: Source, https://github.com/malkiAbdoo/mailshell
Project-URL: Tracker, https://github.com/joelibaceta/mailshell/issues
Keywords: terminal,app,email,gmail,shell
Platform: UNKNOWN
Classifier: Intended Audience :: Developers
Classifier: Operating System :: OS Independent
Classifier: Programming Language :: Python :: 3
Classifier: Programming Language :: Python :: 3.6
Classifier: Programming Language :: Python :: 3.7
Classifier: Programming Language :: Python :: 3.10
Classifier: License :: OSI Approved :: MIT License
Requires-Dist: html-text
Requires-Dist: pwinput
Requires-Dist: requests
